ALU.v
/*****************************************************************************
 *
 *ALU module for 12 bit Microcontoller
 *Inputs : Operand1 (8 bits), Operand2 (8bits), Enable, Mode(4 bits), 
 *		   CurrentFlags (4 bits)
 *Outputs: Result (8 bits), Flags(4 bits)  
 *
 *Reference:
 *http://www.fpga4student.com/2016/11/verilog-hdl-implementation-of-micro.html
 *****************************************************************************/

module ALU(
 	input Enable,
 	input  [7:0] Operand1,
 	input  [7:0] Operand2,
 	input  [3:0] Mode,
 	input  [3:0] Cflags,
 	output [7:0] Result,
 	output [3:0] Flags
 	);

 	reg  [7:0] Result;				// Store the final result
 	reg  Carry;						// Store the carry for the next bit operation
 	reg [3:0] Flags;

 	always@(*) begin				// For every change in the inputs
 	if (Enable == 0) begin
 		Result = 0;
 		Flags = 0;
 	end

 	else begin

		case(Mode)

			//Addition M-Type
			4'b0000: 
			begin
				{Carry, Result} = Operand1 + Operand2;
				if((Operand1[7] == Operand2[7]) && (Result[7] == Operand1[7])) 
				begin
					Flags[0] = 1'b1;
				end
				else 
				begin
					Flags[0] = 1'b0;
				end
				Flags[1] = Result[7];

				if (Result == 0)
					Flags[3] = 1'b0;
				Flags[2] = Carry;
			end
			
			//Subtraction M-Type
			4'b0001: 
			begin
				{Carry, Result} = Operand1 - Operand2;

				if((Operand1[7] == Operand2[7]) && (Result[7] != Operand1[7])) 
					Flags[0] = 1'b1;
				else
					Flags[0] = 1'b0;

				Flags[1] = Result[7];
				Flags[2] = Carry;
				if (Result == 0)
					Flags[3] = 1'b0;
			end

			//Move Acc to Mem
			4'b0010: Result = Operand1;

			//Move Mem to Acc
	  		4'b0011: Result = Operand2;
			
	  		//AND M-Type
			4'b0100: 
			begin
				Result = Operand1 & Operand2;
				if (Result == 0)
					Flags[3] = 1'b0;
			end
			//OR M-Type
			4'b0101: 
			begin
				Result = Operand1 | Operand2;
				if (Result == 0)
					Flags[3] = 1'b0;
			end

			//XOR M-Type
			4'b0110: 
			begin
				Result = Operand1 ^ Operand2;
				if (Result == 0)
					Flags[3] = 1'b0;
			end

			//Sutraction Mem to Acc 
			4'b0111:
			begin
				{Carry, Result} = Operand1 - Operand2;

				if((Operand1[7] == Operand2[7]) && (Result[7] != Operand1[7])) 
					Flags[0] = 1'b1;
				else
					Flags[0] = 1'b0;

				Flags[1] = Result[7];
				if (Result == 0)
					Flags[3] = 1'b0;
			end

			//Increment by 1
			4'b1000:
			begin
				{Carry, Result} = Operand1 + 8'h1;
				if(Result[7] == Operand1[7]) 
					Flags[0] = 1'b1;
				else
					Flags[0] = 1'b0;

				Flags[1] = Result[7];

				if (Result == 0)
					Flags[3] = 1'b0;
				Flags[2] = Carry;
			end

			//Decrement by 1
			4'b1001:
			begin
				{Carry, Result} = Operand1 - 8'h1;
				if(Result[7] == Operand1[7]) 
					Flags[0] = 1'b1;
				else
					Flags[0] = 1'b0;

				Flags[1] = Result[7];
				Flags[2] = Carry;

				if (Result == 0)
					Flags[3] = 1'b0;
			end

			//Rotate Left
			4'b1010: Result=(Operand2 << Operand1[2:0])|(Operand2>>Operand1[2:0]);
			
			//Rotate Right
			4'b1011: Result=(Operand2 >> Operand1[2:0])|(Operand2<<Operand1[2:0]);
			
			//Shift Left Logical
			4'b1100: Result = Operand2 << Operand1[2:0];
	  	
		  	//Shift Right Logical
		  	4'b1101: Result = Operand2 >> Operand1[2:0];
			
			//Shift Right Arithmatic
			4'b1110: Result = Operand2 >>> Operand1[2:0];

			//Complement
			4'b1111:
			begin
				{Carry, Result} = 8'h0 - Operand1;
				if(Result[7] == Operand1[7]) 
					Flags[0] = 1'b1;
				else
					Flags[0] = 1'b0;

				Flags[1] = Result[7];
				Flags[2] = Carry;

				if (Result == 0)
					Flags[3] = 1'b0;
			end
			default: Result = Operand2;
		endcase
	end
end
endmodule

ALU_tb.v
/*****************************************************************************
 *
 *TestBench for ALU module
 *Inputs : Operand1 (8 bits), Operand2 (8bits), Enable, Mode(4 bits), 
 *		   CurrentFlags (4 bits)
 *Outputs: Result (8 bits), Flags(4 bits)  
 *
 *Reference:
 *http://www.fpga4student.com/2016/11/verilog-hdl-implementation-of-micro.html
 *****************************************************************************/

 module ALU_tb;

 reg en;
 reg [7:0] op1;
 reg [7:0] op2;
 reg [3:0] mode;
 reg [3:0] cflags;

 wire [7:0] result;
 wire [3:0] flags_out;

 ALU uut(
 .Enable(en),
 .Operand1(op1),
 .Operand2(op2),
 .Mode(mode),
 .Cflags(cflags),
 .Result(result),
 .Flags(flags_out)
 );

 initial begin

 op1 = 8'h0;
 op2 = 8'h0;
 en = 1'b0;

 #10;

 op1 = 8'hFC;
 op2 = 8'h8;
 en = 1'b1;

 #20 mode = 4'b0000;
 #20 mode = 4'b0001;
 #20 mode = 4'b0010;
 #20 mode = 4'b0011;
 #20 mode = 4'b0100;
 #20 mode = 4'b0101;
 #20 mode = 4'b0110;
 #20 mode = 4'b0111;
 #20 mode = 4'b1000;
 #20 mode = 4'b1001;
 #20 mode = 4'b1010;
 #20 mode = 4'b1011;
 #20 mode = 4'b1100;
 #20 mode = 4'b1101;
 #20 mode = 4'b1110;
 #20 mode = 4'b1111;
 #50;
 end

 initial begin
 $dumpfile("alu.vcd");
 $dumpvars;
 end
 endmodule

vcd/alu.vcd
$date
	Sun Jun  3 11:58:56 2018
$end
$version
	Icarus Verilog
$end
$timescale
	1s
$end
$scope module ALU_tb $end
$var wire 4 ! flags_out [3:0] $end
$var wire 8 " result [7:0] $end
$var reg 4 # cflags [3:0] $end
$var reg 1 $ en $end
$var reg 4 % mode [3:0] $end
$var reg 8 & op1 [7:0] $end
$var reg 8 ' op2 [7:0] $end
$scope module uut $end
$var wire 4 ( Cflags [3:0] $end
$var wire 1 ) Enable $end
$var wire 4 * Mode [3:0] $end
$var wire 8 + Operand1 [7:0] $end
$var wire 8 , Operand2 [7:0] $end
$var reg 1 - Carry $end
$var reg 4 . Flags [3:0] $end
$var reg 8 / Result [7:0] $end
$upscope $end
$upscope $end
$enddefinitions $end
#0
$dumpvars
b0 /
b0 .
x-
b0 ,
b0 +
bx *
0)
bx (
b0 '
b0 &
bx %
0$
bx #
b0 "
b0 !
$end
#10
b1000 /
b1000 "
1$
1)
b1000 '
b1000 ,
b11111100 &
b11111100 +
#30
b100 !
b100 .
1-
b100 /
b100 "
b0 %
b0 *
#50
b10 !
b10 .
0-
b11110100 /
b11110100 "
b1 %
b1 *
#70
b11111100 /
b11111100 "
b10 %
b10 *
#90
b1000 /
b1000 "
b11 %
b11 *
#110
b100 %
b100 *
#130
b11111100 /
b11111100 "
b101 %
b101 *
#150
b11110100 /
b11110100 "
b110 %
b110 *
#170
b10 .
b111 %
b111 *
#190
b11 .
b11 !
b11111101 /
b11111101 "
b1000 %
b1000 *
#210
b11 .
b11111011 /
b11111011 "
b1001 %
b1001 *
#230
b10000000 /
b10000000 "
b1010 %
b1010 *
#250
b1011 %
b1011 *
#270
b1100 %
b1100 *
#290
b0 /
b0 "
b1101 %
b1101 *
#310
b1110 %
b1110 *
#330
b100 .
b100 !
1-
b100 /
b100 "
b1111 %
b1111 *
