DMem.v
/*****************************************************************************
 *
 *Data Memory module (256 bytes) for 12 bit Microcontoller
 *Inputs : Input_data (8 bits), Enable, Write_Enable, Address_port(4 bits) 
 *		   and Clock
 *Outputs: Output_data (8bits)  
 *
 *Reference:
 *http://www.fpga4student.com/2016/11/verilog-hdl-implementation-of-micro.html
 *****************************************************************************/
 module DMem(
 	input clk,
 	input Enable,
 	input Write_en,
 	input [3:0] Address_port,
 	input [7:0] Input_data,
 	output [7:0] Output_data
 );

 reg [7:0] data_mem [255:0]; 

 always@(posedge clk)
 begin
 	if(Enable == 1 && Write_en == 1)
 		data_mem[Address_port] <= Input_data;
 end
 assign Output_data = (Enable == 1)? data_mem[Address_port]:0;
 endmodule

DMem_tb.v
/*****************************************************************************
 *
 *Data Memory Test Bench (256 bytes) for 12 bit Microcontoller
 *Inputs : In_data (8 bits), En, W_En, Addr_port(4 bits) and clk
 *
 *Outputs: Out_data (8bits)  
 *
 *Reference:
 *http://www.fpga4student.com/2016/11/verilog-hdl-implementation-of-micro.html
 *****************************************************************************/

 module DMem_tb;

 reg clk, En, W_En;
 reg [7:0] In_data;
 reg [3:0] Addr_port;
 wire [7:0] Out_data;

 DMem uut(
 .clk(clk),
 .Enable(En),
 .Write_en(W_En),
 .Address_port(Addr_port),
 .Input_data(In_data),
 .Output_data(Out_data)
 );

 initial

 clk = 1'b1;
 always #10 clk = ~clk;

 initial begin
	clk = 1'b0;
	En = 1'b0;
	W_En = 1'b0;
	Addr_port = 4'h0;
	In_data = 0;

	#10 En = 1'b1;
	#10 W_En = 1'b1;

	#10 Addr_port = 4'h0; In_data = 8'hAB;
	#10 Addr_port = 4'h1; In_data = 8'h90;
	#10 Addr_port = 4'h5; In_data = 8'hFF;
	#10 Addr_port = 4'h8; In_data = 8'h12;
	#10 Addr_port = 4'hA; In_data = 8'h34;
	#10 Addr_port = 4'hF; In_data = 8'h75;
	#10 Addr_port = 4'hB; In_data = 8'h64;
	#10 Addr_port = 4'h9; In_data = 8'hFE;

	#10 W_En = 1'b0;
	#10 Addr_port = 4'hA;
	#10 Addr_port = 4'h2;
	#10 Addr_port = 4'hF;
	#10 Addr_port = 4'hC;
	#50;
	$finish;
 end
 initial begin
 	$dumpfile("dmem.vcd");
	$dumpvars;
 end
 endmodule

vcd/dmem.vcd
$date
	Sun Jun  3 11:58:56 2018
$end
$version
	Icarus Verilog
$end
$timescale
	1s
$end
$scope module DMem_tb $end
$var wire 8 ! Out_data [7:0] $end
$var reg 4 " Addr_port [3:0] $end
$var reg 1 # En $end
$var reg 8 $ In_data [7:0] $end
$var reg 1 % W_En $end
$var reg 1 & clk $end
$scope module uut $end
$var wire 4 ' Address_port [3:0] $end
$var wire 1 ( Enable $end
$var wire 8 ) Input_data [7:0] $end
$var wire 8 * Output_data [7:0] $end
$var wire 1 + Write_en $end
$var wire 1 , clk $end
$upscope $end
$upscope $end
$enddefinitions $end
#0
$dumpvars
0,
0+
b0 *
b0 )
0(
b0 '
0&
0%
b0 $
0#
b0 "
b0 !
$end
#10
bx !
bx *
1#
1(
1&
1,
#20
1%
1+
0&
0,
#30
b10101011 !
b10101011 *
b10101011 $
b10101011 )
1&
1,
#40
bx !
bx *
b10010000 $
b10010000 )
b1 "
b1 '
0&
0,
#50
b11111111 !
b11111111 *
b11111111 $
b11111111 )
b101 "
b101 '
1&
1,
#60
bx !
bx *
b10010 $
b10010 )
b1000 "
b1000 '
0&
0,
#70
b110100 !
b110100 *
b110100 $
b110100 )
b1010 "
b1010 '
1&
1,
#80
bx !
bx *
b1110101 $
b1110101 )
b1111 "
b1111 '
0&
0,
#90
b1100100 !
b1100100 *
b1100100 $
b1100100 )
b1011 "
b1011 '
1&
1,
#100
bx !
bx *
b11111110 $
b11111110 )
b1001 "
b1001 '
0&
0,
#110
0%
0+
1&
1,
#120
b110100 !
b110100 *
b1010 "
b1010 '
0&
0,
#130
bx !
bx *
b10 "
b10 '
1&
1,
#140
b1111 "
b1111 '
0&
0,
#150
b1100 "
b1100 '
1&
1,
