Control_Logic.v
/*****************************************************************************
 *
 *Control Unit for 12 bit Microcontoller
 *Inputs : Instr_Reg (12 bits), State(2 bits), Status_Reg(4 bits)
 *
 *Outputs: ProgCounter_En, Acc_En, StatusReg_En, InstrReg_En, DataMemWrite_En,
 * 		   ALU_En, MUX1_Sel, MUX2_Sel, DataMem_En, ProgMem_En, ALU_Mode, 
 *		   ProgMemLoad_En
 *
 *Reference:
 *http://www.fpga4student.com/2016/11/verilog-hdl-implementation-of-micro.html
 *****************************************************************************/
 module Control_Logic(
 input [11:0] Instr_Reg,
 input [1:0] State,
 input [3:0] Status_Reg,
 output ProgCounter_En, Acc_En, StatusReg_En, InstrReg_En, ProgMem_En, 
 output DataMemWrite_En, ALU_En, MUX1_Sel, DataMem_En, DataReg_En, MUX2_Sel,
 output ProgMemLoad_En,
 output [3:0] ALU_Mode
 );

 parameter LOAD = 2'b00, FETCH = 2'b01, DECODE = 2'b10, EXECUTE = 2'b11;

 reg ProgCounter_En, Acc_En, StatusReg_En, InstrReg_En, ProgMem_En;
 reg DataMemWrite_En, ALU_En, MUX1_Sel, DataMem_En, DataReg_En, MUX2_Sel;
 reg ProgMemLoad_En;
 reg [3:0] ALU_Mode;

 always@(*)
 begin

 	//Initialize all the signals at every input change.
 	ProgMemLoad_En = 0;
	ProgCounter_En = 0;
	Acc_En = 0;
	StatusReg_En = 0;
	InstrReg_En = 0;
	ProgMem_En = 0;
	DataMemWrite_En = 0;
	ALU_En = 0;
	MUX1_Sel = 0;
	DataMem_En = 0;
	DataReg_En = 0;
	MUX2_Sel = 0;
	ALU_Mode = 4'h0;

	// Load State -> Enable the Program Memory and the Load Signal
	if(State == LOAD)
	begin
		ProgMemLoad_En = 1'b1;
		ProgMem_En = 1'b1;
	end

	//Fetch State -> Fetch the instruction from Program Memory and load it to IR
	else if (State == FETCH)
	begin
		InstrReg_En = 1'b1;
		ProgMem_En = 1'b1;
	end

	//Decode State -> Decode the instr in the IR and send it to ALU and other modules
	//Instruction Register = {Instruction Type(11:8), Opcode(11:8)/Immediate(7:4), 
	//						  Immediate_value/DMem_Addr(3:1) }
	//
 	else if (State == DECODE)
 	begin
 		if (Instr_Reg[11:9] == 3'b001)	// M-type
 		begin
 			DataReg_En = 1'b1; 
 			DataMem_En = 1'b1;
 		end
 		else
 		begin
 			DataReg_En = 1'b0;
 			DataMem_En = 1'b0;
 		end
 	end

 	else if (State == EXECUTE)
 	begin
 		if (Instr_Reg[11] == 1'b1) // I-Type Operation
 		begin
 			ProgCounter_En = 1'b1; // Take current Instr_Addr
 			Acc_En = 1'b1; // Since I-Type, Operand2 for ALU -> Accumulator
 			StatusReg_En = 1'b1; //Enable Status Register
 			ALU_En = 1'b1; //Enable ALU
 			ALU_Mode = Instr_Reg[10:8]; //Opcode in I-Type-> 4'b1xxx
 			MUX1_Sel = 1; // Take the next Instruction Addr from Adder
 			MUX2_Sel = 0; // Do not take value from Memory
 		end
 		else if(Instr_Reg[11:10] == 2'b01) //JZ, JC, JS, JO
 		begin
 			ProgCounter_En = 1'b1;
 			MUX1_Sel = Status_Reg[Instr_Reg[9:8]];
 		end
 		else if(Instr_Reg[9] == 1'b1) // Execute M-type Instruction
 		begin
 			ProgCounter_En = 1'b1;
 			Acc_En = Instr_Reg[8];
 			StatusReg_En = 1'b1;
 			DataMem_En = !(Instr_Reg[8]);
 			DataMemWrite_En = !(Instr_Reg[8]);
 			ALU_En = 1'b1;
 			ALU_Mode = Instr_Reg[7:4];
 			MUX1_Sel = 1'b1;
 			MUX2_Sel = 1'b1;
 		end
 		else if(Instr_Reg[8] == 1'b0)
 		begin
 			ProgCounter_En = 1'b1;
 			MUX1_Sel = 1'b1;
 		end
 		else
 		begin
 			ProgCounter_En = 1'b0;
 			MUX1_Sel = 1'b0;
 		end
 	end
 end
 endmodule

Adder.v
/*****************************************************************************
 *
 *Adder for 12 bit Microcontoller
 *Inputs : In_data (8 bits)
 *
 *Outputs: Out_data (8bits)  
 *
 *Reference:
 *http://www.fpga4student.com/2016/11/verilog-hdl-implementation-of-micro.html
 *****************************************************************************/

 module Adder(
 	input [7:0] In_data,
 	output [7:0] Out_data
 );

 assign Out_data = In_data + 1;
 endmodule

PMem.v
/*****************************************************************************
 *
 *Program Memory (256 bytes) for 12 bit Microcontoller
 *Inputs : Instr_port (12 bits), En, Load_En, clk, Load_Addr(8 bits),
 *		   Load_Instr(12 bits)  
 *
 *Outputs: Out_data (8bits)  
 *
 *Reference:
 *http://www.fpga4student.com/2016/11/verilog-hdl-implementation-of-micro.html
 *****************************************************************************/

 module PMem(
 	input clk,
 	input En,
 	input [7:0] Addr,
 	input Load_En,
 	input [7:0] Load_Addr,
 	input [11:0]Load_Instr,
 	output [11:0] Instr
 );

 reg [11:0] Prog_Mem[255:0];

 always@(posedge clk)
 begin
 	if(Load_En) begin
 		Prog_Mem[Load_Addr] <= Load_Instr;
 	end
 end

 assign Instr = (En == 1)? Prog_Mem[Addr]:0;
 endmodule

DMem.v
/*****************************************************************************
 *
 *Data Memory module (256 bytes) for 12 bit Microcontoller
 *Inputs : Input_data (8 bits), Enable, Write_Enable, Address_port(4 bits) 
 *		   and Clock
 *Outputs: Output_data (8bits)  
 *
 *Reference:
 *http://www.fpga4student.com/2016/11/verilog-hdl-implementation-of-micro.html
 *****************************************************************************/
 module DMem(
 	input clk,
 	input Enable,
 	input Write_en,
 	input [3:0] Address_port,
 	input [7:0] Input_data,
 	output [7:0] Output_data
 );

 reg [7:0] data_mem [255:0]; 

 always@(posedge clk)
 begin
 	if(Enable == 1 && Write_en == 1)
 		data_mem[Address_port] <= Input_data;
 end
 assign Output_data = (Enable == 1)? data_mem[Address_port]:0;
 endmodule

MUX1.v
/*****************************************************************************
 *
 *Multiplexer 1 for 12 bit Microcontoller
 *Inputs : Input1 (8 bits), Input2(8 bits), Select 
 *
 *Outputs: Out (8bits)  
 *
 *Reference:
 *http://www.fpga4student.com/2016/11/verilog-hdl-implementation-of-micro.html
 *****************************************************************************/

 module MUX1(
 	input [7:0] Input1, Input2,
 	input Sel,
 	output [7:0] Out
 );

 assign Out = (Sel == 1)? Input1: Input2;
 endmodule

ALU.v
/*****************************************************************************
 *
 *ALU module for 12 bit Microcontoller
 *Inputs : Operand1 (8 bits), Operand2 (8bits), Enable, Mode(4 bits), 
 *		   CurrentFlags (4 bits)
 *Outputs: Result (8 bits), Flags(4 bits)  
 *
 *Reference:
 *http://www.fpga4student.com/2016/11/verilog-hdl-implementation-of-micro.html
 *****************************************************************************/

module ALU(
 	input Enable,
 	input  [7:0] Operand1,
 	input  [7:0] Operand2,
 	input  [3:0] Mode,
 	input  [3:0] Cflags,
 	output [7:0] Result,
 	output [3:0] Flags
 	);

 	reg  [7:0] Result;				// Store the final result
 	reg  Carry;						// Store the carry for the next bit operation
 	reg [3:0] Flags;

 	always@(*) begin				// For every change in the inputs
 	if (Enable == 0) begin
 		Result = 0;
 		Flags = 0;
 	end

 	else begin

		case(Mode)

			//Addition M-Type
			4'b0000: 
			begin
				{Carry, Result} = Operand1 + Operand2;
				if((Operand1[7] == Operand2[7]) && (Result[7] == Operand1[7])) 
				begin
					Flags[0] = 1'b1;
				end
				else 
				begin
					Flags[0] = 1'b0;
				end
				Flags[1] = Result[7];

				if (Result == 0)
					Flags[3] = 1'b0;
				Flags[2] = Carry;
			end
			
			//Subtraction M-Type
			4'b0001: 
			begin
				{Carry, Result} = Operand1 - Operand2;

				if((Operand1[7] == Operand2[7]) && (Result[7] != Operand1[7])) 
					Flags[0] = 1'b1;
				else
					Flags[0] = 1'b0;

				Flags[1] = Result[7];
				Flags[2] = Carry;
				if (Result == 0)
					Flags[3] = 1'b0;
			end

			//Move Acc to Mem
			4'b0010: Result = Operand1;

			//Move Mem to Acc
	  		4'b0011: Result = Operand2;
			
	  		//AND M-Type
			4'b0100: 
			begin
				Result = Operand1 & Operand2;
				if (Result == 0)
					Flags[3] = 1'b0;
			end
			//OR M-Type
			4'b0101: 
			begin
				Result = Operand1 | Operand2;
				if (Result == 0)
					Flags[3] = 1'b0;
			end

			//XOR M-Type
			4'b0110: 
			begin
				Result = Operand1 ^ Operand2;
				if (Result == 0)
					Flags[3] = 1'b0;
			end

			//Sutraction Mem to Acc 
			4'b0111:
			begin
				{Carry, Result} = Operand1 - Operand2;

				if((Operand1[7] == Operand2[7]) && (Result[7] != Operand1[7])) 
					Flags[0] = 1'b1;
				else
					Flags[0] = 1'b0;

				Flags[1] = Result[7];
				if (Result == 0)
					Flags[3] = 1'b0;
			end

			//Increment by 1
			4'b1000:
			begin
				{Carry, Result} = Operand1 + 8'h1;
				if(Result[7] == Operand1[7]) 
					Flags[0] = 1'b1;
				else
					Flags[0] = 1'b0;

				Flags[1] = Result[7];

				if (Result == 0)
					Flags[3] = 1'b0;
				Flags[2] = Carry;
			end

			//Decrement by 1
			4'b1001:
			begin
				{Carry, Result} = Operand1 - 8'h1;
				if(Result[7] == Operand1[7]) 
					Flags[0] = 1'b1;
				else
					Flags[0] = 1'b0;

				Flags[1] = Result[7];
				Flags[2] = Carry;

				if (Result == 0)
					Flags[3] = 1'b0;
			end

			//Rotate Left
			4'b1010: Result=(Operand2 << Operand1[2:0])|(Operand2>>Operand1[2:0]);
			
			//Rotate Right
			4'b1011: Result=(Operand2 >> Operand1[2:0])|(Operand2<<Operand1[2:0]);
			
			//Shift Left Logical
			4'b1100: Result = Operand2 << Operand1[2:0];
	  	
		  	//Shift Right Logical
		  	4'b1101: Result = Operand2 >> Operand1[2:0];
			
			//Shift Right Arithmatic
			4'b1110: Result = Operand2 >>> Operand1[2:0];

			//Complement
			4'b1111:
			begin
				{Carry, Result} = 8'h0 - Operand1;
				if(Result[7] == Operand1[7]) 
					Flags[0] = 1'b1;
				else
					Flags[0] = 1'b0;

				Flags[1] = Result[7];
				Flags[2] = Carry;

				if (Result == 0)
					Flags[3] = 1'b0;
			end
			default: Result = Operand2;
		endcase
	end
end
endmodule

MCU.v
/*****************************************************************************
 *
 *12 bit Microcontoller (simplified version)
 *Harvard Architecture, Non-pipelined
 *Inputs : clk (1 bit), reset(1 bit)
 *
 *Reference:
 *http://www.fpga4student.com/2016/11/verilog-hdl-implementation-of-micro.html
 *****************************************************************************/
 module MCU(
 	input clk, rst
 );

 //Initialize States.
 parameter LOAD = 2'b00, FETCH=2'b01, DECODE=2'b10, EXECUTE = 2'b11;
 
 //Initialize Registers and Memory
 reg LoadDone;
 reg ProgCounter_Clr, Accumulator_Clr, StatusReg_Clr, DataReg_Clr, InstrReg_Clr;
 reg[1:0] currentState, nextState;
 reg[3:0] StatusReg;
 reg[7:0] LoadAddr;
 reg[7:0] ProgCounter, DataReg, Accumulator;
 reg[11:0] InstrReg;
 reg[11:0] ProgMem[9:0];

 //Initialize all signals 
 wire ProgCounter_En, Accumulator_En, StatusReg_En, DataReg_En, InstrReg_En; 
 wire ProgMem_En, DataMem_En, DataMem_WEn, ALU_En, ProgMem_LEn, MUX1_Sel, MUX2_Sel;
 wire[3:0] StatusReg_Updated;
 wire[3:0] ALU_Mode;
 wire[7:0] AdderOut;
 wire[7:0] ALU_Out, ALU_Operand2;
 wire[7:0] ProgCounter_Updated, DataReg_Updated;
 wire[11:0] InstrReg_Updated;
 wire[11:0] LoadInstr;

 //LOAD all the 10 instructions to Memory
 initial
 begin
 $readmemb("/home/shanbhag/Desktop/Verilog_Projects/MCU/tests/case1.dat", ProgMem, 0, 9);
 end
 
 //ALU
 ALU ALU_unit(
 .Operand1(Accumulator),
 .Operand2(ALU_Operand2),
 .Enable(ALU_En),
 .Mode(ALU_Mode),
 .Cflags(StatusReg),
 .Result(ALU_Out),
 .Flags(StatusReg_Updated)
 );

 //MUX1
 MUX1 MUX1_unit(
 .Input1(AdderOut),
 .Input2(InstrReg[7:0]),
 .Sel(MUX1_Sel),
 .Out(ProgCounter_Updated)
 );

 //MUX2
 MUX1 MUX2_unit(
 .Input1(DataReg),
 .Input2(InstrReg[7:0]),
 .Sel(MUX2_Sel),
 .Out(ALU_Operand2)
 );

 //Data Memory
 DMem DMem_unit(
 .clk(clk),
 .Enable(DataMem_En),
 .Write_en(DataMem_WEn),
 .Address_port(InstrReg[3:0]),
 .Input_data(ALU_Out),
 .Output_data(DataReg_Updated)
 );

 //Program Memory
 PMem PMem_unit(
 .clk(clk),
 .En(ProgMem_En),
 .Addr(ProgCounter),
 .Load_En(ProgMem_LEn),
 .Load_Addr(LoadAddr),
 .Load_Instr(LoadInstr),
 .Instr(InstrReg_Updated)
 );

 //Adder
 Adder PC_Adder_unit(
 .In_data(ProgCounter),
 .Out_data(AdderOut)
 );

 //Control Unit
 Control_Logic Control_Logic_unit(
 .Instr_Reg(InstrReg),
 .State(currentState),
 .Status_Reg(StatusReg),
 .ProgCounter_En(ProgCounter_En),
 .Acc_En(Accumulator_En),
 .StatusReg_En(StatusReg_En),
 .InstrReg_En(InstrReg_En),
 .ProgMem_En(ProgMem_En),
 .DataMemWrite_En(DataMem_WEn),
 .ALU_En(ALU_En),
 .MUX1_Sel(MUX1_Sel),
 .MUX2_Sel(MUX2_Sel),
 .DataMem_En(DataMem_En),
 .DataReg_En(DataReg_En),
 .ProgMemLoad_En(ProgMem_LEn),
 .ALU_Mode(ALU_Mode)
 );

 //LOAD consequent instructions from the programMem to LoadInstr for every posedge.
 always @(posedge clk) 
 begin
 	if(rst == 1)
 	begin
 		LoadAddr <= 0;
 		LoadDone <= 1'b0;
 	end
 	else if(ProgMem_LEn == 1'b1)
 	begin
 		LoadAddr <= LoadAddr+8'd1;
	 	if(LoadAddr == 8'd9)
	 	begin
	 		LoadAddr <= 8'd0;
	 		LoadDone <= 1'b1;
	 	end
	 	else
	 	begin
	 		LoadDone <= 1'b0;
	 	end
	end
 end
 assign LoadInstr = ProgMem[LoadAddr];

 //Go to the next state at every posedge.
 always @(posedge clk)
 begin
 	//if rst then set the state initially to Load.
 	if(rst == 1)
 		currentState <= LOAD;
 	//Else whatever is the next state.
 	else
 		currentState <= nextState;
 end

 //For every change in clk
 always @(*)
 begin
 	ProgCounter_Clr = 0; 
 	Accumulator_Clr = 0;
 	StatusReg_Clr = 0; 
 	DataReg_Clr = 0;
 	InstrReg_Clr = 0;
 	case(currentState)
 	
	 	LOAD:
	 	begin
	 	//After Load, set the nextState to FETCH and clear all the registers. 
	 		if(LoadDone == 1)
	 		begin
	 			nextState = FETCH;
	 			ProgCounter_Clr = 1; 
	 			Accumulator_Clr = 1;
	 			StatusReg_Clr = 1; 
	 			DataReg_Clr = 1;
	 			InstrReg_Clr = 1;
	 		end
	 		else
	 		nextState = LOAD;
	 	end

	 	FETCH:
	 	begin
	 		nextState = DECODE;
	 	end

	 	DECODE:
	 	begin
	 		nextState = EXECUTE;
	 	end

	 	EXECUTE:
	 	begin
	 		nextState = FETCH; // These are blocking assignments. Hence, happens 
	 	end

 	endcase
 end

 //Update Program Counter, Accumulator and Status Register for every 
 //posedge of clock.
 always @(posedge clk)
 begin
 	if(rst == 1)
 	begin
 		ProgCounter <= 8'd0;
 		Accumulator <= 8'd0;
 		StatusReg 	<= 8'd0;
 	end
 	else
 	begin
 		if(ProgCounter_En == 1'b1)
 			ProgCounter = ProgCounter_Updated;
 		else if (ProgCounter_Clr == 1)
 			ProgCounter = 8'd0;
 		if(Accumulator_En == 1'b1)
 			Accumulator <= ALU_Out;
 		else if(Accumulator_Clr == 1)
 			Accumulator <= 8'd0;
 		if(StatusReg_En == 1'b1)
 			StatusReg <= StatusReg_Updated;
 		else if(StatusReg_Clr == 1)
 			StatusReg <= 4'd0;
 	end
 end

 //Update the Data Register and Program Register.
 always @(posedge clk)
 begin
 	if(DataReg_En == 1'b1)
 		DataReg <= DataReg_Updated;
 	else if(DataReg_Clr == 1)
 		DataReg <= 8'd0;
 	if(InstrReg_En == 1'b1)
 		InstrReg <= InstrReg_Updated;
 	else if(InstrReg_Clr == 1)
 		InstrReg <= 12'd0;
 end
 endmodule

MCU_tb.v
/*****************************************************************************
 *
 *Microcontroller Test Bench
 *Inputs : Clock and Reset
 *
 *Outputs: None. Check all Module Outputs after every clock cycle.  
 *
 *Reference:
 *http://www.fpga4student.com/2016/11/verilog-hdl-implementation-of-micro.html
 *****************************************************************************/

 module MCU_tb;

 reg clk;
 reg rst;

 MCU MCU_UUT(
 	.clk(clk),
 	.rst(rst)
 );

 initial 
 begin

	 //Initialize Inputs
	 rst = 1;

	 //Wait till all modules reset.
	 #100;
	 rst = 0;
 end

 initial begin
 	$dumpfile("mcu.vcd");
	$dumpvars;
 end
 
 initial 
 begin
 	clk = 0;
 	repeat(600)
 	begin
 		#1 clk = ~clk;
 	end
 end
 endmodule

vcd/mcu.vcd
$date
	Wed Jul 18 12:32:33 2018
$end
$version
	Icarus Verilog
$end
$timescale
	1s
$end
$scope module MCU_tb $end
$var reg 1 ! clk $end
$var reg 1 " rst $end
$scope module MCU_UUT $end
$var wire 1 # ALU_En $end
$var wire 4 $ ALU_Mode [3:0] $end
$var wire 8 % ALU_Operand2 [7:0] $end
$var wire 8 & ALU_Out [7:0] $end
$var wire 1 ' Accumulator_En $end
$var wire 8 ( AdderOut [7:0] $end
$var wire 1 ) DataMem_En $end
$var wire 1 * DataMem_WEn $end
$var wire 1 + DataReg_En $end
$var wire 8 , DataReg_Updated [7:0] $end
$var wire 1 - InstrReg_En $end
$var wire 12 . InstrReg_Updated [11:0] $end
$var wire 12 / LoadInstr [11:0] $end
$var wire 1 0 MUX1_Sel $end
$var wire 1 1 MUX2_Sel $end
$var wire 1 2 ProgCounter_En $end
$var wire 8 3 ProgCounter_Updated [7:0] $end
$var wire 1 4 ProgMem_En $end
$var wire 1 5 ProgMem_LEn $end
$var wire 1 6 StatusReg_En $end
$var wire 4 7 StatusReg_Updated [3:0] $end
$var wire 1 8 clk $end
$var wire 1 9 rst $end
$var reg 8 : Accumulator [7:0] $end
$var reg 1 ; Accumulator_Clr $end
$var reg 8 < DataReg [7:0] $end
$var reg 1 = DataReg_Clr $end
$var reg 12 > InstrReg [11:0] $end
$var reg 1 ? InstrReg_Clr $end
$var reg 8 @ LoadAddr [7:0] $end
$var reg 1 A LoadDone $end
$var reg 8 B ProgCounter [7:0] $end
$var reg 1 C ProgCounter_Clr $end
$var reg 4 D StatusReg [3:0] $end
$var reg 1 E StatusReg_Clr $end
$var reg 2 F currentState [1:0] $end
$var reg 2 G nextState [1:0] $end
$scope module ALU_unit $end
$var wire 4 H Cflags [3:0] $end
$var wire 1 # Enable $end
$var wire 4 I Mode [3:0] $end
$var wire 8 J Operand1 [7:0] $end
$var wire 8 K Operand2 [7:0] $end
$var reg 1 L Carry $end
$var reg 4 M Flags [3:0] $end
$var reg 8 N Result [7:0] $end
$upscope $end
$scope module MUX1_unit $end
$var wire 8 O Input1 [7:0] $end
$var wire 8 P Input2 [7:0] $end
$var wire 8 Q Out [7:0] $end
$var wire 1 0 Sel $end
$upscope $end
$scope module MUX2_unit $end
$var wire 8 R Input1 [7:0] $end
$var wire 8 S Input2 [7:0] $end
$var wire 8 T Out [7:0] $end
$var wire 1 1 Sel $end
$upscope $end
$scope module DMem_unit $end
$var wire 4 U Address_port [3:0] $end
$var wire 1 ) Enable $end
$var wire 8 V Input_data [7:0] $end
$var wire 8 W Output_data [7:0] $end
$var wire 1 * Write_en $end
$var wire 1 8 clk $end
$upscope $end
$scope module PMem_unit $end
$var wire 8 X Addr [7:0] $end
$var wire 1 4 En $end
$var wire 12 Y Instr [11:0] $end
$var wire 8 Z Load_Addr [7:0] $end
$var wire 1 5 Load_En $end
$var wire 12 [ Load_Instr [11:0] $end
$var wire 1 8 clk $end
$upscope $end
$scope module PC_Adder_unit $end
$var wire 8 \ In_data [7:0] $end
$var wire 8 ] Out_data [7:0] $end
$upscope $end
$scope module Control_Logic_unit $end
$var wire 12 ^ Instr_Reg [11:0] $end
$var wire 2 _ State [1:0] $end
$var wire 4 ` Status_Reg [3:0] $end
$var reg 1 a ALU_En $end
$var reg 4 b ALU_Mode [3:0] $end
$var reg 1 c Acc_En $end
$var reg 1 d DataMemWrite_En $end
$var reg 1 e DataMem_En $end
$var reg 1 f DataReg_En $end
$var reg 1 g InstrReg_En $end
$var reg 1 h MUX1_Sel $end
$var reg 1 i MUX2_Sel $end
$var reg 1 j ProgCounter_En $end
$var reg 1 k ProgMemLoad_En $end
$var reg 1 l ProgMem_En $end
$var reg 1 m StatusReg_En $end
$upscope $end
$upscope $end
$upscope $end
$enddefinitions $end
#0
$dumpvars
xm
xl
xk
xj
xi
xh
xg
xf
xe
xd
xc
bx b
xa
bx `
bx _
bx ^
bx ]
bx \
bx [
bx Z
bx Y
bx X
bx W
bx V
bx U
bx T
bx S
bx R
bx Q
bx P
bx O
bx N
bx M
xL
bx K
bx J
bx I
bx H
bx G
bx F
xE
bx D
xC
bx B
xA
bx @
x?
bx >
x=
bx <
x;
bx :
19
08
bx 7
x6
x5
x4
bx 3
x2
x1
x0
bx /
bx .
x-
bx ,
x+
x*
x)
bx (
x'
bx &
bx %
bx $
x#
1"
0!
$end
#1
b0 ,
b0 W
b0 M
b0 7
b0 N
b0 &
b0 V
b0 G
0?
0=
0E
0;
0C
b0 b
b0 $
b0 I
0i
01
0f
0+
0e
0)
0h
00
0a
0#
0d
0*
1l
14
0g
0-
0m
06
0c
0'
0j
02
1k
15
b1 (
b1 O
b1 ]
0A
b0 @
b0 /
b0 [
b0 Z
b0 F
b0 _
b0 D
b0 H
b0 `
b0 :
b0 J
b0 B
b0 X
b0 \
1!
18
#2
0!
08
#3
b0 .
b0 Y
1!
18
#4
0!
08
#5
1!
18
#6
0!
08
#7
1!
18
#8
0!
08
#9
1!
18
#10
0!
08
#11
1!
18
#12
0!
08
#13
1!
18
#14
0!
08
#15
1!
18
#16
0!
08
#17
1!
18
#18
0!
08
#19
1!
18
#20
0!
08
#21
1!
18
#22
0!
08
#23
1!
18
#24
0!
08
#25
1!
18
#26
0!
08
#27
1!
18
#28
0!
08
#29
1!
18
#30
0!
08
#31
1!
18
#32
0!
08
#33
1!
18
#34
0!
08
#35
1!
18
#36
0!
08
#37
1!
18
#38
0!
08
#39
1!
18
#40
0!
08
#41
1!
18
#42
0!
08
#43
1!
18
#44
0!
08
#45
1!
18
#46
0!
08
#47
1!
18
#48
0!
08
#49
1!
18
#50
0!
08
#51
1!
18
#52
0!
08
#53
1!
18
#54
0!
08
#55
1!
18
#56
0!
08
#57
1!
18
#58
0!
08
#59
1!
18
#60
0!
08
#61
1!
18
#62
0!
08
#63
1!
18
#64
0!
08
#65
1!
18
#66
0!
08
#67
1!
18
#68
0!
08
#69
1!
18
#70
0!
08
#71
1!
18
#72
0!
08
#73
1!
18
#74
0!
08
#75
1!
18
#76
0!
08
#77
1!
18
#78
0!
08
#79
1!
18
#80
0!
08
#81
1!
18
#82
0!
08
#83
1!
18
#84
0!
08
#85
1!
18
#86
0!
08
#87
1!
18
#88
0!
08
#89
1!
18
#90
0!
08
#91
1!
18
#92
0!
08
#93
1!
18
#94
0!
08
#95
1!
18
#96
0!
08
#97
1!
18
#98
0!
08
#99
1!
18
#100
0!
08
0"
09
#101
b1 @
b101100000001 /
b101100000001 [
b1 Z
1!
18
#102
0!
08
#103
b10 @
b1000100000 /
b1000100000 [
b10 Z
1!
18
#104
0!
08
#105
b11 @
b101100000000 /
b101100000000 [
b11 Z
1!
18
#106
0!
08
#107
b100 @
b1100110000 /
b1100110000 [
b100 Z
1!
18
#108
0!
08
#109
b101 @
b100000101 /
b100000101 [
b101 Z
1!
18
#110
0!
08
#111
b110 @
b0 /
b0 [
b110 Z
1!
18
#112
0!
08
#113
b111 @
b111 Z
1!
18
#114
0!
08
#115
b1000 @
b1000 Z
1!
18
#116
0!
08
#117
b1001 @
b1001 Z
1!
18
#118
0!
08
#119
1?
1=
1E
1;
1C
b1 G
1A
b0 @
b0 /
b0 [
b0 Z
1!
18
#120
0!
08
#121
b0 3
b0 Q
b0 %
b0 K
b0 T
b10 G
0?
0=
0E
0;
0C
b0 P
b0 S
b0 U
1g
1-
1l
14
0k
05
0A
b1 @
b101100000001 /
b101100000001 [
b1 Z
b1 F
b1 _
b0 >
b0 ^
b0 <
b0 R
1!
18
#122
0!
08
#123
0l
04
0g
0-
b11 G
b10 F
b10 _
1!
18
#124
0!
08
#125
b1 3
b1 Q
1h
10
1j
12
b1 G
b11 F
b11 _
1!
18
#126
0!
08
#127
b101100000001 .
b101100000001 Y
1l
14
1g
1-
0h
00
0j
02
b10 G
b1 F
b1 _
b0 3
b0 Q
b10 (
b10 O
b10 ]
b1 B
b1 X
b1 \
1!
18
#128
0!
08
#129
b1 3
b1 Q
b1 %
b1 K
b1 T
b0 .
b0 Y
b11 G
b1 P
b1 S
b1 U
0l
04
0g
0-
b10 F
b10 _
b101100000001 >
b101100000001 ^
1!
18
#130
0!
08
#131
b10 3
b10 Q
b1 N
b1 &
b1 V
1h
10
b11 b
b11 $
b11 I
1a
1#
1m
16
1c
1'
1j
12
b1 G
b11 F
b11 _
1!
18
#132
0!
08
#133
b1000100000 .
b1000100000 Y
b0 N
b0 &
b0 V
1l
14
1g
1-
b0 b
b0 $
b0 I
0h
00
0a
0#
0m
06
0c
0'
0j
02
b10 G
b1 F
b1 _
b1 :
b1 J
b1 3
b1 Q
b11 (
b11 O
b11 ]
b10 B
b10 X
b10 \
1!
18
#134
0!
08
#135
b100000 3
b100000 Q
b100000 %
b100000 K
b100000 T
bx ,
bx W
b0 .
b0 Y
b100000 P
b100000 S
b0 U
1e
1)
1f
1+
0l
04
0g
0-
b11 G
b1000100000 >
b1000100000 ^
b10 F
b10 _
1!
18
#136
0!
08
#137
bx %
bx K
bx T
b11 3
b11 Q
b1 N
b1 &
b1 V
1i
11
1h
10
b10 b
b10 $
b10 I
1a
1#
1d
1*
1m
16
1j
12
0f
0+
1e
1)
b1 G
b11 F
b11 _
bx <
bx R
1!
18
#138
0!
08
#139
b101100000000 .
b101100000000 Y
b100000 %
b100000 K
b100000 T
b0 N
b0 &
b0 V
1l
14
1g
1-
b0 b
b0 $
b0 I
0i
01
0e
0)
0h
00
0a
0#
0d
0*
0m
06
0j
02
b10 G
b0 ,
b0 W
b1 F
b1 _
b100000 3
b100000 Q
b100 (
b100 O
b100 ]
b11 B
b11 X
b11 \
1!
18
#140
0!
08
#141
b0 3
b0 Q
b0 %
b0 K
b0 T
b0 .
b0 Y
b11 G
b0 P
b0 S
0l
04
0g
0-
b10 F
b10 _
b101100000000 >
b101100000000 ^
1!
18
#142
0!
08
#143
b100 3
b100 Q
1h
10
b11 b
b11 $
b11 I
1a
1#
1m
16
1c
1'
1j
12
b1 G
b11 F
b11 _
1!
18
#144
0!
08
#145
b1100110000 .
b1100110000 Y
1l
14
1g
1-
b0 b
b0 $
b0 I
0h
00
0a
0#
0m
06
0c
0'
0j
02
b10 G
b1 F
b1 _
b0 :
b0 J
b0 3
b0 Q
b101 (
b101 O
b101 ]
b100 B
b100 X
b100 \
1!
18
#146
0!
08
#147
b110000 3
b110000 Q
b110000 %
b110000 K
b110000 T
b1 ,
b1 W
b0 .
b0 Y
b110000 P
b110000 S
1e
1)
1f
1+
0l
04
0g
0-
b11 G
b1100110000 >
b1100110000 ^
b10 F
b10 _
1!
18
#148
0!
08
#149
b1 %
b1 K
b1 T
b101 3
b101 Q
b1 N
b1 &
b1 V
b0 ,
b0 W
1i
11
1h
10
b11 b
b11 $
b11 I
1a
1#
1m
16
1c
1'
1j
12
0f
0+
0e
0)
b1 G
b11 F
b11 _
b1 <
b1 R
1!
18
#150
0!
08
#151
b100000101 .
b100000101 Y
b110000 %
b110000 K
b110000 T
b0 N
b0 &
b0 V
1l
14
1g
1-
b0 b
b0 $
b0 I
0i
01
0h
00
0a
0#
0m
06
0c
0'
0j
02
b10 G
b1 :
b1 J
b1 F
b1 _
b110000 3
b110000 Q
b110 (
b110 O
b110 ]
b101 B
b101 X
b101 \
1!
18
#152
0!
08
#153
b101 3
b101 Q
b101 %
b101 K
b101 T
b0 .
b0 Y
b11 G
b101 P
b101 S
b101 U
0l
04
0g
0-
b10 F
b10 _
b100000101 >
b100000101 ^
1!
18
#154
0!
08
#155
b1 G
b11 F
b11 _
1!
18
#156
0!
08
#157
b100000101 .
b100000101 Y
1l
14
1g
1-
b10 G
b1 F
b1 _
1!
18
#158
0!
08
#159
b0 .
b0 Y
0l
04
0g
0-
b11 G
b10 F
b10 _
1!
18
#160
0!
08
#161
b1 G
b11 F
b11 _
1!
18
#162
0!
08
#163
b100000101 .
b100000101 Y
1l
14
1g
1-
b10 G
b1 F
b1 _
1!
18
#164
0!
08
#165
b0 .
b0 Y
0l
04
0g
0-
b11 G
b10 F
b10 _
1!
18
#166
0!
08
#167
b1 G
b11 F
b11 _
1!
18
#168
0!
08
#169
b100000101 .
b100000101 Y
1l
14
1g
1-
b10 G
b1 F
b1 _
1!
18
#170
0!
08
#171
b0 .
b0 Y
0l
04
0g
0-
b11 G
b10 F
b10 _
1!
18
#172
0!
08
#173
b1 G
b11 F
b11 _
1!
18
#174
0!
08
#175
b100000101 .
b100000101 Y
1l
14
1g
1-
b10 G
b1 F
b1 _
1!
18
#176
0!
08
#177
b0 .
b0 Y
0l
04
0g
0-
b11 G
b10 F
b10 _
1!
18
#178
0!
08
#179
b1 G
b11 F
b11 _
1!
18
#180
0!
08
#181
b100000101 .
b100000101 Y
1l
14
1g
1-
b10 G
b1 F
b1 _
1!
18
#182
0!
08
#183
b0 .
b0 Y
0l
04
0g
0-
b11 G
b10 F
b10 _
1!
18
#184
0!
08
#185
b1 G
b11 F
b11 _
1!
18
#186
0!
08
#187
b100000101 .
b100000101 Y
1l
14
1g
1-
b10 G
b1 F
b1 _
1!
18
#188
0!
08
